svreg/__init__.py
svreg/svreg.py
svreg-0.1.0.post2.dist-info/LICENSE.MD
svreg-0.1.0.post2.dist-info/WHEEL
svreg-0.1.0.post2.dist-info/METADATA
svreg-0.1.0.post2.dist-info/RECORD
